{"time_collected":"2023-03-19 19:14:27.167323-04:00","top_headers":[{"heading":"Interior update","time_posted":"10 hours ago"},{"heading":"Happy to be back in the Nissan fam!","time_posted":"6 hours ago"},{"heading":"Akebonos installed! Update: Splitters way too low for New England lol","time_posted":"4 hours ago"}],"rules":["#1"],"subreddits":{"Related Communities":{"r/Nissan":"66,646 members","r/350z":"35,540 members","r/ft86":"58,528 members","r/mazda3":"58,611 members","r/genesiscoupe":"8,694 members","r/JDM":"277,450 members","r/BMWE36":"20,228 members","r/camaro":"38,331 members","r/FocusST":"30,924 members","r/Rivian":"54,570 members"}},"about":{"header":"About Community","description":"A place for all 370Z enthusiasts to come together and discuss their love for the most important letter in the alphabet.","created":"Created Aug 10, 2012","stats":["20.4k Enthusiasts","64 Online"]},"other_information":[]}