{"time_collected":"2023-03-07 04:40:12.023252-05:00","top_headers":[{"heading":"r/Celebhub has reached 900,000 members!","time_posted":"2 days ago"},{"heading":"Ellie Kemper","time_posted":"18 hours ago"},{"heading":"Samara Weaving [The Babysitter]","time_posted":"13 hours ago"},{"heading":"Alice Eve [Star Trek Into Darkness]","time_posted":"13 hours ago"},{"heading":"Kat Dennings","time_posted":"8 hours ago"},{"heading":"Deborah Ann Woll Cleavage","time_posted":"13 hours ago"},{"heading":"Peyton List","time_posted":"7 hours ago"}],"rules":["Suitable content","Banned content","Age guidelines","Title guidelines","NSFW content","Altered content","Quality guidelines","Repost guidelines","Crosspost guidelines","Post limits and host","Comment guidelines","Repeated violations of these guidelines will result in a temporary or permanent ban"],"subreddits":{"Recommended Subreddits":{"r/CelebBattles":"161,445 members"}},"about":{"header":"About Community","description":"Famous actresses, singers, models, athletes and other beautiful celebs.","created":"Created May 5, 2018","stats":["901k Members","1.1k Online"]},"other_information":[{"header":"Useful Links","description":"A-Z Celebrity List • Hall of Fame • Actresses • Singers • Models • Athletes • Celebrity Nationalities"}]}