{"time_collected":"2023-03-07 08:13:21.467631-05:00","top_headers":[{"heading":"The Big Kahuna Megathread: “Hell, there are no rules here – we’re trying to accomplish something.” - Thomas Edison","time_posted":"4 months ago"},{"heading":"A Memorial to the Folly of Cindy","time_posted":"1 month ago"},{"heading":"There’s now Voices for Freedom online radio for people who find The Platform too woke","time_posted":"10 hours ago"},{"heading":"The Big Pump","time_posted":"7 hours ago"},{"heading":"Census Spies 2023","time_posted":"13 hours ago"},{"heading":"New Definition SCIENCE - the systematic study of the structure and behaviour of the physical and natural world through observation, experimentation, and the testing of theories against the evidence obtained. AND Matauranga Maori","time_posted":"19 hours ago"}],"rules":["No shills or throw away accounts","No bullying or trolling","No racism or extremism","Lighten up sometimes","No calls to violence or doxing","No concern trolling","No thread crashing","Video submissions.","No usernames or pinging unless done in good faith"],"subreddits":{"Related Communities":{"r/newzealand":"390,042 members","r/australia":"1,133,191 members","r/ireland":"640,874 members","r/Snorkblot":"8,228 members","r/ScottishFootball":"48,570 members","r/southafrica":"201,976 members","r/Quebec":"249,968 members","r/AustralianPolitics":"225,456 members","r/northernireland":"181,459 members","r/auckland":"109,359 members"}},"about":{"header":"About Community","description":"A New Zealand subreddit, run by conservatives. Anyone is welcome to join this subreddit, regardless of political position. A place to have discussion and share interests on anything NZ related.","created":"Created Apr 17, 2019","stats":["7.8k Curious Chaps","24 Sub Snacking"]},"other_information":[]}