{"time_collected":"2023-03-19 18:12:29.581763-04:00","top_headers":[{"heading":"Dance Gavin Dance shares statement regarding Tilian Pearson","time_posted":"4 months ago"},{"heading":"As promised, the finished DGD poster I designed. Thanks to everyone who helped fill in “You’ll wonder why Jon is…?”","time_posted":"18 hours ago"},{"heading":"Opinions on Jackpot Juicer Songs: Day 2 - Synergy","time_posted":"4 hours ago"},{"heading":"Got my favorite lyrics tattooed today 😌","time_posted":"22 hours ago"},{"heading":"Hey you!","time_posted":"29 minutes ago"}],"rules":["Spam","Leaks/File-sharing","No sales","Don't Be A Dick"],"subreddits":{"Related Communities":{"r/Metalcore":"372,107 members","r/RedHotChiliPeppers":"95,430 members","r/poppunkers":"113,654 members","r/Foofighters":"77,510 members","r/bmbmbm":"17,360 members","r/Emo":"135,557 members","r/stickyfingers":"6,217 members","r/deftones":"58,588 members","r/Hardcore":"95,743 members","r/the1975":"60,872 members"}},"about":{"header":"About Community","description":"A subreddit for fans of the post-hardcore band Dance Gavin Dance. News, discussions, live videos, covers, side-projects and much more. Make sure you're viewing the sub off mobile for the best experience, where you can view our menu bar for endless DGD resources.","created":"Created Dec 14, 2011","stats":["51.8k Members","79 Online","Top 5% Ranked by Size"]},"other_information":[]}