{"time_collected":"2023-03-07 03:45:26.855477-05:00","top_headers":[{"heading":"American Fascism And The Groomer Panic","time_posted":"8 days ago"},{"heading":"You deserve the fruits of your labor","time_posted":"19 hours ago"},{"heading":"It’s almost like people that benefit off of exploiting the poor are the scum of the earth!","time_posted":"2 days ago"},{"heading":"good cop bad cop","time_posted":"1 day ago"}],"rules":["No Reactionaries","Left unity is enforced here.","Follow Reddit rules","Only post memes","Only post leftist content","No memes or advocacy for pro-capitalist ideologies, politicians, or parties, including progressives"],"subreddits":{},"about":{"header":"About Community","description":"This is a subreddit for Marxists, Anarchists, and DemSocs, with only the most dank and most left memes. Proletarians of all nations, unite! Seize the memes of production! You have nothing to lose but your frown!","created":"Created May 15, 2019","stats":["187k Dank Leftists","76 Scheming Revolutionaries"]},"other_information":[{"header":"Endorsed communities","description":"r/AntifascistsofReddit - bash the fash!\nr/FixedPoliticalMemes - Seize the memes from the bourgeoisie!\nr/ShitLiberalsSay - lib cringe\nr/HotTakeCentral - Pictures with wacky fonts?\nr/AustraliaLeftPolitics - Politics & Memes for Aussie Leftists\nr/WorkersStrikeBack - for the workers\nr/BreadTube - youtube, but for leftists"}]}