{"time_collected":"2023-03-07 03:08:24.984326-05:00","top_headers":[{"heading":"TES 6 Speculation Megathread","time_posted":"1 year ago"},{"heading":"Be honest...who's the real homie?","time_posted":"10 hours ago"},{"heading":"Slave drip","time_posted":"8 hours ago"},{"heading":"Don't worry guys they'll each get at least one.","time_posted":"8 hours ago"}],"rules":["Reddiquette","Off-topic","NSFW","Excessive Promotion","Wrong Give away format","Spoilers","Piracy","Rumours","No Flair","Repost","No RP/Gimmick accounts","AI"],"subreddits":{},"about":{"header":"About Community","description":"The Elder Scrolls (commonly referred to as TES) is an award-winning series of roleplaying games created by Bethesda Softworks. Set in the vast world of Nirn, The Elder Scrolls series is renowned for the level of unprecedented control given the player over his or her character's destiny, establishing itself as the benchmark in immersive, independently-living worlds for the RPG genre.","created":"Created Aug 26, 2010","stats":["423k Members","462 Online"]},"other_information":[]}