{"time_collected":"2023-03-07 05:30:34.910673-05:00","top_headers":[{"heading":"Join the r/F1Game Discord for leagues, lobbies or to be the first to get notified of new patches","time_posted":"4 months ago"},{"heading":"r/F1Game Weekly Discussion & Questions Thread - 2023 March 02","time_posted":"5 days ago"},{"heading":"Following the screenshot, here's my 90% worn tyre final lap from my league's race.","time_posted":"11 hours ago"},{"heading":"Internally screaming to finish this league race. 😅","time_posted":"22 hours ago"},{"heading":"As much as we shit on the rest of F1 22 can we give the soundtrack guy credit for killing it.","time_posted":"11 hours ago"}],"rules":["No Spam","Civility and Respect","Memes must be related to the F1 games","No Piracy or Fraud","Feedback","No League Advertisements or Requests","No Twitch Stream Link Posts","No self-promotion","Sharing messages/arguments about who is at fault for an incident will result in a ban","Posts related to the F1 Manager games should be directed to r/F1Manager"],"subreddits":{"/r/F1Game's Friends":{"r/formula1":"2,937,785 members","r/simracing":"281,094 members","r/F1Manager":"23,363 members"}},"about":{"header":"About Community","description":"The best community for all F1 games. F1 Esports Pro Series starts on September 14th! Banner by u/Oli695","created":"Created Sep 29, 2014","stats":["193k racers","293 telling Jeff to shut up"]},"other_information":[]}