{"time_collected":"2023-03-20 01:27:50.433085-04:00","top_headers":[{"heading":"/r/FormerPizzaHuts Identification Guide & Posting Guidelines","time_posted":"3 years ago"},{"heading":"3611 Kirkwood Hwy. Wilmington, DE. Old Pizza Hut recently changed to a diner.","time_posted":"1 day ago"},{"heading":"A shuttered Urgent Care right on the Brattleboro, VT/Keene, NH line","time_posted":"2 days ago"},{"heading":"I found this abandoned location in Colorado city Texas it closed during Covid","time_posted":"2 days ago"}],"rules":["Post only images of former Pizza Hut locations","Treat all participants with respect","No recent reposts"],"subreddits":{"Related Subreddits":{"r/FormerBlockbusters":"4,853 members","r/FormerTacoBells":"6,309 members","r/NotFoolingAnybody":"31,647 members","r/repurposedbuildings":"257,922 members","r/RetailNostalgia":"1,579 members","r/retailporn":"30,883 members","r/youseeingthisshit":"2,444,816 members"}},"about":{"header":"About Community","description":"Yes, everything really is on Reddit. This subreddit is dedicated to recognizable Former Pizza Hut locations. Why? Well, because we wanted to.","created":"Created Jun 11, 2016","stats":["74.7k Members","8 Online","Top 5% Ranked by Size"]},"other_information":[]}