{"time_collected":"2023-03-08 16:10:01.488908-05:00","top_headers":[{"heading":"Here's a list of methods you SHOULDN'T use to verify games, with helpful visual guides.","time_posted":"8 days ago"},{"heading":"Don't be a cunt. Be Like Dave.","time_posted":"13 hours ago"},{"heading":"my Pokémon platinum copy is it legitimate?","time_posted":"4 hours ago"},{"heading":"Zelda Phantom Hourglass, real?","time_posted":"2 hours ago"}],"rules":["⚠️ Before You Post - Verification Requirements","⚠️ Before You Post - Post Requirements","❓ \"Why Can't I Post?\" & FAQs","✉️ Mod Mail & Directly Messaging Staff","❌ No Spreading Misinformation","2️⃣ No Resubmissions","🤝 Be Disciplined & Respectful"],"subreddits":{"Related Communities":{"r/LegitCheck":"19,610 members","r/basketballjerseys":"17,243 members","r/FearofGod":"7,312 members","r/pkmntcgcollections":"39,891 members","r/Arrowheads":"34,489 members","r/PokemonTCG":"228,964 members","r/skylanders":"30,069 members","r/supremeclothing":"189,272 members","r/bapeheads":"24,900 members","r/GameboyAdvance":"19,016 members"}},"about":{"header":"About Community","description":"Wondering if your games are fake or not? Want to share your experiences with real, fake or repro carts? Have some suspect video game covers, consoles and/or discs? This is the place for you. https://gameverifying.com/","created":"Created Nov 29, 2019","stats":["17.4k Members","76 Online"]},"other_information":[]}