{"time_collected":"2023-03-06 22:41:29.660918-05:00","top_headers":[{"heading":"Community feedback/metapost for March 2023","time_posted":"5 days ago"},{"heading":"Do some Israeli Jews secretly support Hamas (or at least appreciate its existence)?","time_posted":"1 hour ago"},{"heading":"Palestinian Arabs origin?","time_posted":"9 hours ago"},{"heading":"The Jewish people are the human expression of the land of Israel","time_posted":"6 hours ago"},{"heading":"Why does Israel NEED to be a “homeland for Jewish people”?","time_posted":"11 hours ago"},{"heading":"Condolences for the people of Huwara","time_posted":"7 days ago"},{"heading":"Putin paying Palestinians in Lebanon refugee camps to fight in Ukraine","time_posted":"7 days ago"},{"heading":"Why do the the Arabs gatekeep everything from Israelis, even if it's not something exclusively Arab?","time_posted":"7 days ago"},{"heading":"Ali Abunimah and Electronic Intifada Declare Remembering the Holocaust is Anti-Palestinian","time_posted":"7 days ago"}],"rules":["No attacks on fellow users","No profanity","No posts/comments consisting solely of sarcasm or cynicism.","Be honest","Constructive Criticism","Nazi comparisons & Discussions","No metaposting","Don't discourage participation","Avoid vague claims of bias","At least 3 paragraphs","Include several common refutations","Don't delete posts","Respond to moderation warnings cooperatively not combatively"],"subreddits":{"Related Communities":{"r/Israel_Palestine":"4,875 members","r/arabs":"80,689 members","r/AskMiddleEast":"40,758 members","r/islam":"229,260 members","r/Israel":"189,031 members","r/Judaism":"82,897 members","r/IDF":"4,283 members","r/BDS":"5,902 members","r/ForbiddenBromance":"3,795 members","r/PoaleZion":"509 members"}},"about":{"header":"About Community","description":"A subreddit dedicated to promoting civil conversation on issues relating to Israel and Palestine.","created":"Created May 4, 2011","stats":["30.4k Members","46 Online"]},"other_information":[{"header":"Wiki","description":"Please refer to our Wiki for basic information about Israel and Palestine, detailed descriptions and explanations of our rules, and additional resources.\nShort list of Rules\nRecommended Reading page of various topics. message the mods to add content."},{"header":"Collections","description":"The following are groups of posts talking about a single subject.\nBest of\nBest of 2022\nMiscellaneous\nMedia Recommendation to learn about the Israeli/Palestinian Conflict\nThrough Arab Eyes Series\nSolutions\nOne State Solution\nThe Confederation Solution\nBDS\nEvents\n2023.2.23 Huwara\n2023.1.28 Jerusalem Synagogue Terror Attack\n2022.11 Farha Movie Controversy\n2022.8.5 Operation Breaking Dawn\n2022.6 West Bank extension of emergency law\n2022.5.29 Flag March\n2022.5.11 Shireen Abu Akleh\n2022.2.24 Russia/Ukraine war & the Israeli/Palestinian Conflict\n2021 Hanukkah"},{"header":"Unofficial Discord Server","description":"Click to Join"}]}