{"time_collected":"2023-03-06 22:14:17.780581-05:00","top_headers":[{"heading":"Original Content ONLY","time_posted":"6 years ago"},{"heading":"Customer came back after we did an oil change on a Subaru, stating it had problems, new guy drained the transmission","time_posted":"6 hours ago"},{"heading":"Vehicle was towed in over the weekend. Customer didnt leave any contact info or the key. No way to contact them to determine their complaint.","time_posted":"11 hours ago"}],"rules":["Original Content ONLY","Posts Need Not Be Automotive Related, But Must Follow Rule 1","No Help or Troubleshooting Posts","Must include a detailed description of problem or failure.","No Memes. No Rage Comics.","No posts from Facebook, Twitter, Instagram, etc.","Please Mark NSFW when applicable","Please cover or remove license plate numbers, VINs, phone numbers, and names.","No \"spotted pictures\" (eg: something you saw in the parking lot)","Discussion posts are allowed, but cannot be mechanic advice or help advice.","No for sale posts","Trend posts or karma trains are at moderator discretion"],"subreddits":{"Visit Our Friends!":{"r/AskAShittyMechanic":"38,939 members","r/AutoDetailing":"752,719 members","r/carporn":"1,683,612 members","r/Cartalk":"618,079 members","r/MechanicAdvice":"1,156,905 members","r/Shitty_Car_Mods":"1,292,115 members","r/spotted":"201,961 members"}},"about":{"header":"About Community","description":"For those absolutely stupid things that you see people bring, roll, or toss into your place of business and the people that bring them in.","created":"Created Mar 29, 2012","stats":["2.0m Confused Mechanics","5.7k Confused Mechanics"]},"other_information":[]}