{"time_collected":"2023-03-08 17:36:41.297540-05:00","top_headers":[{"heading":"What's Working and What Isn't? - Monday, March 06, 2023","time_posted":"2 days ago"},{"heading":"Ask r/LoRCompetitive - Wednesday, March 08, 2023","time_posted":"3 hours ago"},{"heading":"7 New and Revamped Off-Meta Decks for Ranked in Patch 4.2","time_posted":"8 hours ago"},{"heading":"Deck Guide: A dad finally makes it to Masters... with a Nasus/Helia Combo Deck","time_posted":"6 hours ago"},{"heading":"Monday Meta Report - Patch 4.2, March 6th","time_posted":"2 days ago"},{"heading":"Ask r/LoRCompetitive - Saturday, February 25, 2023","time_posted":"11 days ago"},{"heading":"By the Numbers – Twenty-One Best Decks, According to the Latest Data","time_posted":"12 days ago"},{"heading":"Patch 4.1 Masters Climbing Guide #4: Rockbear Lissandra Taliyah and RubinZoo's Shyvana Fiora","time_posted":"12 days ago"},{"heading":"What's Working and What Isn't? - Thursday, February 23, 2023","time_posted":"13 days ago"},{"heading":"Ask r/LoRCompetitive - Wednesday, February 22, 2023","time_posted":"14 days ago"},{"heading":"Patch 4.1 Masters Climbing Guide #3: Jayce Lux Ferros Control & Illaoi Master Yi Combo","time_posted":"16 days ago"},{"heading":"LoR Meta Report – Patch 4.1 Week 2 - Best Ladder Decks - Norra Everywhere","time_posted":"16 days ago"},{"heading":"What's Working and What Isn't? - Monday, February 20, 2023","time_posted":"16 days ago"}],"rules":["All posts must be on-topic and focus on the competitive side of LoR.","No hate speech or personal insults. Use common courtesy.","No posts asking for deckbuilding help or basic questions allowed.","Discussions need to have OP's analysis in sufficient depth.","Deck posts must be sufficiently in depth.","Winrates in titles or other clickbait titles are not allowed.","Posts must be properly formatted.","All off-site articles or videos must be posted with an explanation or summary.","Patch notes or card reveal posts need permission.","No excessive self-promotion.","Event / tournament posts need approval by mod team.","No low effort posts or \"unpopular opinion\" posts allowed.","No NSFW Content, no Memes or Fluff allowed.","No meta discussion of Riot Games allowed.","Full Rules"],"subreddits":{"Other LoR Subreddits":{"r/LegendsOfRuneterra":"192,888 members","r/CustomLoR":"12,884 members","r/LoRCirclejerk":"5,531 members"}},"about":{"header":"About Community","description":"The competitive hub for all things Legends of Runeterra. Come improve and learn together!","created":"Created Oct 16, 2019","stats":["21.3k Members","29 Online"]},"other_information":[]}