{"time_collected":"2023-03-19 20:15:52.288010-04:00","top_headers":[{"heading":"LoseIt Video Games Challenge | RESULTS","time_posted":"27 days ago"},{"heading":"Missed signups? Want to be reminded of the next challenge?","time_posted":"1 month ago"},{"heading":"LOG YO SHIZZ - BOT POST","time_posted":"28 days ago"},{"heading":"Team Mario Week 6 Wrap-Up","time_posted":"1 month ago"},{"heading":"LoseIt Video Games Challenge | WEEK 7 | BATTLE ROYALE","time_posted":"1 month ago"},{"heading":"Legend of Zelda Week 6 Check-in","time_posted":"1 month ago"},{"heading":"Team Pokemon Week 6 Check-In","time_posted":"1 month ago"},{"heading":"Stardew Valley: Welcome to Year 6","time_posted":"1 month ago"},{"heading":"Stardew Valley Week 4 Wrap-up & Week 5 Hype-up","time_posted":"2 months ago"},{"heading":"Legend of Zelda Week 4 Recap","time_posted":"2 months ago"},{"heading":"LoseIt Video Games Challenge | WEEK 5 UPDATE AND LINKS","time_posted":"2 months ago"},{"heading":"LOG YO SHIZZ - BOT POST","time_posted":"2 months ago"},{"heading":"Team Pokemon Week 4 Check-In!","time_posted":"2 months ago"},{"heading":"Team Mario: Week 3 Recap","time_posted":"2 months ago"},{"heading":"Join the Ultrawalkathon (8) Server!","time_posted":"2 months ago"},{"heading":"Sardew Valley: W3 Recap","time_posted":"2 months ago"},{"heading":"Legend of Zelda week 3 update","time_posted":"2 months ago"},{"heading":"LoseIt Video Games Challenge | WEEK 4 UPDATE AND LINKS | WALKATHON THIS SATURDAY (JAN 28)","time_posted":"2 months ago"},{"heading":"walkathon reminder!","time_posted":"2 months ago"},{"heading":"LOG YO SHIZZ - BOT POST","time_posted":"2 months ago"},{"heading":"Team Pokemon Week 3 Check-In","time_posted":"2 months ago"},{"heading":"LoseIt Video Games Challenge | WEEK 3 UPDATE AND LINKS","time_posted":"2 months ago"},{"heading":"Legend of Zelda: Week 2 Recap","time_posted":"2 months ago"},{"heading":"LOG YO SHIZZ - BOT POST","time_posted":"2 months ago"},{"heading":"I heard you like walking? 👀","time_posted":"2 months ago"}],"rules":["Be kind","No self promotion.","No Medical Advice."],"subreddits":{},"about":{"header":"About Community","description":"Welcome to the January 2023 Challenge! Signups are open until January 9th.","created":"Created Aug 18, 2019","stats":["10.1k Members","1 Online"]},"other_information":[{"header":"Schedule","description":"Each week starts at 12pm EST on a Monday. Entries for that week close then and a new week begins.\nSpring 2023 Challenge Schedule\nWeek 1 | Sign-ups (Practice round) | Jan 2-8\nWeek 2 | Beginning of head-to-heads, sign-ups closed | Jan 9-15\nWeek 3 | Head-to-head | Jan 16-22\nWeek 4 | Head-to-head | Jan 23-29\nWalkathon 8 - Jan 28\nWeek 5 | Head-to-head | Jan 30-Feb 5\nWeek 6 | Head-to-head | Feb 6-Feb 12\nWeek 7 | Battle Royale | Feb 13-Feb 19\nResults | Feb 20"}]}