{"time_collected":"2023-03-19 18:29:24.612218-04:00","top_headers":[{"heading":"[META] Please obey the subreddit rules, ESPECIALLY rules 3 and 9.","time_posted":"7 years ago"},{"heading":"If someone messages you, advertising a service/app, based on your activity here, REPORT IT TO REDDIT.","time_posted":"3 years ago"},{"heading":"Integral 2^x-x^2 between 1 and -1 help","time_posted":"10 hours ago"},{"heading":"Is there a way to do this algebraicly?","time_posted":"6 hours ago"},{"heading":"How do you explain why the sum to infinity exists for the surface area of revolution formula","time_posted":"13 hours ago"},{"heading":"A sequence goes 1, 1, 1, 4, 27, 3125. Find the 16th term in the sequence.","time_posted":"19 hours ago"},{"heading":"How do I prove that Ln(z1 * z2) = Ln(z1) + Ln(z2) ?","time_posted":"1 day ago"},{"heading":"Definite Intergral","time_posted":"20 hours ago"}],"rules":["Do not ask for help on tests or exams.","Show proof of prior working attempts.","No advertising for paid services of any sort.","Do not delete your posts.","Do not answer any questions that break rules.","Do not give out the answer."],"subreddits":{},"about":{"header":"About Community","description":"A sub for helping you with your mathematics problems! If you're willing to learn, we're willing to teach.","created":"Created May 26, 2009","stats":["34.1k Members","15 Online","Top 5% Ranked by Size"]},"other_information":[]}