{"time_collected":"2023-03-07 01:59:42.671752-05:00","top_headers":[{"heading":"2023 Live Offseason Tracker","time_posted":"11 days ago"},{"heading":"[Tom Pelissero] The #Vikings are releasing veteran linebacker Eric Kendricks, per sources. A first-team All-Pro in 2019 and one of the NFL’s most consistently productive LBs, Kendricks now heads to free agency.","time_posted":"17 hours ago"},{"heading":"[Schefter] Vikings’ WR @KJ_Osborn helped pull a man from a burning car Sunday night before carrying him to safety and helping to save his life. His story here.","time_posted":"7 hours ago"},{"heading":"THANK YOU FOR EVERYTHING ERIC!","time_posted":"17 hours ago"}],"rules":["No Duplicates","Limit on ”Fuck the X” and \"UPVOTE PARTY\" threads","No Personal Attacks","No Politics or Religion or Racism or Sexism or Homophobia","No Direct Linking to Reddit Posts","Behavior in other NFL teams' subs","Memes","Selling tickets","Title quality","Miscellaneous","No Solicitation"],"subreddits":{"Related Communities":{"r/ravens":"143,221 members","r/nfl":"3,636,383 members","r/DynastyFF":"101,760 members","r/GreenBayPackers":"295,717 members","r/CHIBears":"168,355 members","r/Patriots":"702,502 members","r/fantasyfootball":"1,291,474 members","r/CFL":"40,020 members","r/LosAngelesRams":"444,427 members","r/Flyers":"58,046 members"}},"about":{"header":"About Community","description":"SKOL","created":"Created Nov 9, 2008","stats":["191k Members","283 Online"]},"other_information":[]}