{"time_collected":"2023-03-20 18:57:54.672103-04:00","top_headers":[{"heading":"Read All Points (Semi Important)","time_posted":"2 years ago"},{"heading":"giveaway time! apply on main thread","time_posted":"26 days ago"},{"heading":"Looking for heartblade","time_posted":"1 day ago"},{"heading":"Is anything here worth anything or what would this be worth all together?","time_posted":"2 days ago"},{"heading":"Does anyone have the SparkleTime set?? (I use supreme)","time_posted":"2 days ago"},{"heading":"PLEASE CHECK IT OUT","time_posted":"3 days ago"},{"heading":"anyone trading icepiercer i will do almost anything for it","time_posted":"4 days ago"},{"heading":"Trading Robux for MM2","time_posted":"5 days ago"},{"heading":"TRADING THESE","time_posted":"7 days ago"},{"heading":"Anyone want to do this??","time_posted":"7 days ago"}],"subreddits":{},"about":{"header":"About Community","description":"Value and demand traders, win or lose trades, give aways for the community to do their own give aways or join them there is many more things we do to help you with mm2. Rules: No full swearing use a couple letters then hashtags if you dont it's a 3 day ban nsfw = 3 day ban scamming = a lifetime ban (victim must show proof he has been scammed) harassing = a mute bullying = a mute or ban if it's really bad spamming = your post will be deleted or you will get a mute HAVE FUN!","created":"Created Sep 15, 2020","stats":["3.0k Members","3 Online"]},"other_information":[]}