{"time_collected":"2023-03-07 06:10:52.363382-05:00","top_headers":[{"heading":"Academic Studies and Mom Blogs - Monthly","time_posted":"6 days ago"},{"heading":"Could someone please tell me if this is normal?","time_posted":"15 hours ago"},{"heading":"Who’s with me. (Credit to @tamminsursok)","time_posted":"16 hours ago"},{"heading":"My daughter turned 2 months today 🥺❤️","time_posted":"20 hours ago"}],"rules":["No blogs, surveys or promotional posts","Moms only","Be kind","No panhandling","Mod discretion"],"subreddits":{"Related Communities":{"r/beyondthebump":"602,649 members","r/Parenting":"5,227,761 members","r/toddlers":"338,445 members","r/NewParents":"241,429 members","r/sleeptrain":"72,278 members","r/newborns":"20,950 members","r/Nanny":"44,639 members","r/BabyBumps":"342,149 members","r/scabies":"2,729 members","r/Mom":"16,832 members"}},"about":{"header":"About Community","description":"We are moms mucking through the ickier parts of child raising. It may not always be pretty, fun and awesome, but we do it. We want to be here for other moms who are going through the same experiences and offer a helping hand.","created":"Created Sep 4, 2010","stats":["799k Members","655 Online","Top 1% Ranked by Size"]},"other_information":[]}