{"time_collected":"2023-03-07 15:24:39.892828-05:00","top_headers":[{"heading":"Please read the WIKI/FAQ.","time_posted":"2 years ago"},{"heading":"Nothing quite like the new bike day feeling! Bring on the summer.","time_posted":"8 hours ago"},{"heading":"Nice Audi","time_posted":"1 hour ago"},{"heading":"The old Bird passed her ULEZ test with 0.01 NOx to spare","time_posted":"3 hours ago"},{"heading":"had my first proper rtc","time_posted":"10 hours ago"}],"rules":["Sale / Trade","Advert","Civility","Repost Bot"],"subreddits":{"Related Subreddits":{"r/motorcycles":"1,786,078 members","r/Fixxit":"33,785 members","r/motoukforsale":"835 members","r/125R":"522 members","r/ScottishMotorcyclists":"122 members","r/BritishBikerProblems":"295 members","r/projectbike":"6,877 members"}},"about":{"header":"About Community","description":"If you would like to complain about the poor weather, oblivious drivers or the tedious motorcycle license laws, you've come to the right place.","created":"Created Feb 20, 2013","stats":["37.7k Members","174 Online"]},"other_information":[]}