{"time_collected":"2023-03-20 01:59:02.283428-04:00","top_headers":[{"heading":"Advice needed as I approach retirement","time_posted":"5 hours ago"},{"heading":"Words with Friends anyone?","time_posted":"1 hour ago"},{"heading":"New SSA resource available..","time_posted":"3 hours ago"},{"heading":"Center for Retirement Research - this website is of interest to readers here","time_posted":"15 hours ago"},{"heading":"Medicare supplement question","time_posted":"11 hours ago"},{"heading":"Senior care is crushingly expensive. Boomers aren’t ready.","time_posted":"2 days ago"},{"heading":"The Case for a Roth for Individuals in High Tax-Brackets","time_posted":"1 day ago"},{"heading":"Are you risking your income without even knowing it? Shocking truth that&#x27;s affecting life.","time_posted":"12 hours ago"},{"heading":"Medicare, has anyone else experienced this?","time_posted":"5 days ago"},{"heading":"What institutions do you recommend for 401k’s?","time_posted":"4 days ago"}],"subreddits":{"Related Communities":{"r/Fire":"255,570 members","r/FIREUK":"143,147 members","r/povertyfinance":"1,667,536 members","r/AusFinance":"417,333 members","r/irishpersonalfinance":"26,930 members","r/askSingapore":"123,363 members","r/Accounting":"335,912 members","r/OccupationalTherapy":"26,390 members","r/AustralianTeachers":"21,814 members","r/FIREyFemmes":"34,347 members"}},"about":{"header":"About Community","description":"Welcome to retirement","created":"Created Jan 28, 2012","stats":["20.0k Members","28 Online","Top 5% Ranked by Size"]},"other_information":[]}