{"time_collected":"2023-03-19 16:50:09.817568-04:00","top_headers":[{"heading":"New Mod!","time_posted":"4 months ago"},{"heading":"User Flairs","time_posted":"3 months ago"},{"heading":"My Garmin truly understands.","time_posted":"11 hours ago"},{"heading":"when the 5k course joins with the 10k course and i’m forced to run next to a hobby runner. (who isn’t even wearing vaporflys)","time_posted":"3 hours ago"}],"subreddits":{"Related Subs":{"r/running":"2,381,663 members","r/artc":"11,071 members","r/AdvancedRunning":"364,595 members","r/Superadvancedrunning":"111 members","r/runningmemes":"30,201 members","r/RunningShoeGeeks":"77,383 members","r/slowjogging":"5,662 members","r/runningman":"54,551 members"}},"about":{"header":"About Community","description":"Jerker's of all things running.","created":"Created Feb 14, 2012","stats":["23.5k Members","44 Online"]},"other_information":[]}