{"time_collected":"2023-03-19 19:47:22.397878-04:00","top_headers":[{"heading":"Monthly Post: SaaS Deals + Offers","time_posted":"24 days ago"},{"heading":"Weekly Feedback Post - SaaS Products, Ideas, Companies","time_posted":"4 days ago"},{"heading":"I created the cheapest Jasper, Copy.ai & Writesonic alternative on the market - 40+ AI templates with unlimited usage","time_posted":"8 hours ago"},{"heading":"Instructional designers: check out this chrome extension that automatically creates clickable walkthroughs of software and tools for the purpose of learning/teaching","time_posted":"8 hours ago"},{"heading":"How does your startup stay legally compliant","time_posted":"4 hours ago"},{"heading":"Help us Build the Ultimate Software Spend Management Tool","time_posted":"26 minutes ago"},{"heading":"AppExchange or other similar marketplaces","time_posted":"43 minutes ago"},{"heading":"Alternative to InShot (desktop)","time_posted":"2 hours ago"}],"rules":["Submission Guidelines","No Direct Sales Or Non-Productive Self-Promotion","Posting SaaS Relevant Content Only","Blog Posts Rules","Be Kind And Supportive — Criticise Ideas, Not People","Other Bad Behaviour","Politicizing"],"subreddits":{"Related communities":{"r/GrowthHacking":"33,392 members","r/NoCodeSaaS":"1,894 members","r/advancedentrepreneur":"31,983 members"}},"about":{"header":"About Community","description":"Discussions and useful links for SaaS owners, online business owners, and more.","created":"Created Jul 31, 2008","stats":["46.9k SaaS People","77 Online"]},"other_information":[]}