{"time_collected":"2023-03-20 18:34:30.858395-04:00","top_headers":[{"heading":"Official Stupid Questions Thread! Ask /r/stance anything you want to know about cars, stance, or anything else! Don't be shy! Newbies welcome!","time_posted":"4 years ago"},{"heading":"what state you think has the best stanced cars?","time_posted":"4 hours ago"},{"heading":"Soopra","time_posted":"21 hours ago"},{"heading":"Nice","time_posted":"17 hours ago"}],"subreddits":{"Related Communities":{"r/houkai3rd":"153,318 members"}},"about":{"header":"About Community","description":"A subreddit dedicated to slammed cars and cars looking pretty.","created":"Created Mar 10, 2011","stats":["61.0k Members","73 Online","Top 5% Ranked by Size"]},"other_information":[]}