{"time_collected":"2023-03-20 01:38:16.720905-04:00","top_headers":[{"heading":"My discord server is now open to anyone, come and say hi!","time_posted":"3 months ago"},{"heading":"I’ve never seen anything like this. The refraction is not in ROYGBIV order.","time_posted":"5 hours ago"},{"heading":"Stabilized Triple Pendulum System","time_posted":"5 hours ago"},{"heading":"Can you explain a Memoristor using Spintronics?","time_posted":"14 days ago"},{"heading":"Not sure if this has been posted here but","time_posted":"15 days ago"}],"subreddits":{},"about":{"header":"About Community","description":"Official subreddit for the Youtube channel and the person Steve Mould","created":"Created Mar 1, 2018","stats":["4.2k Members","9 Online","Top 10% Ranked by Size"]},"other_information":[]}