{"time_collected":"2023-03-07 03:06:36.275226-05:00","top_headers":[{"heading":"Welcome to /r/Subliminal - Rules & FAQ (Read before posting!)","time_posted":"4 years ago"},{"heading":"Weekly Questions, Subliminal and Creator Recommendation and Discussion Thread 03/06/23","time_posted":"18 hours ago"},{"heading":"results+++decision","time_posted":"16 hours ago"},{"heading":"Is Tulip Beauty Subs good?","time_posted":"3 hours ago"},{"heading":"the fastest Results","time_posted":"16 hours ago"}],"rules":["NSFW must be flagged as such","Posts must be related to the subject of subliminals","Limit your new posts to a maximum of one a day - please don't spam and no self promo.","Treat each other with dignity and respect","Respect the beliefs of others.","No Image Manipulation, You Must Own the Rights to the Images you are Posting.","No Drama Posts","No Low Effort Posts","No Throwaway Accounts","All Sub/Creator Requests Must be Made in the Pinned Weekly Discussion Thread."],"subreddits":{},"about":{"header":"About Community","description":"A community to share, discuss and peer review subliminals that you encounter.","created":"Created Oct 4, 2012","stats":["70.3k Members","224 Online"]},"other_information":[{"header":"Important Note","description":"Subliminal messaging as a concept has polarizing studies about the short and long term effects. You cannot gain super powers, nor change your eye color to something unnatural, nor change your DNA. However you may see results from the power of suggestion and passing messages into your subconscious. Subliminals may also provide new self-awareness, drives, passions, and goals."},{"header":"Wiki Shortcuts","description":"Subliminal Wiki\nApproved Creators\nFAQ\nSubliminal Listening Mini-Guide"}]}