{"time_collected":"2023-03-07 00:44:28.334067-05:00","top_headers":[{"heading":"Simple Questions & Champion/Role advice: Patch 13.3","time_posted":"21 days ago"},{"heading":"Moderation Applications - Spring 2023","time_posted":"28 days ago"},{"heading":"If you're serious about climbing, /deafen is EXTREMELY OP.","time_posted":"14 hours ago"},{"heading":"Which one is stronger? A dash with a short cast time or no cast time at all?","time_posted":"16 hours ago"},{"heading":"Does anyone keep accidentally sliding into 'Bait' ping instead of 'Question mark missing'","time_posted":"10 hours ago"},{"heading":"What is a major learning point in all Elos?","time_posted":"7 hours ago"},{"heading":"What are the components of \"mechanics\"","time_posted":"9 hours ago"},{"heading":"How do i become more consistent as an ADC?","time_posted":"23 hours ago"},{"heading":"8 Game Lose Streak and I don't Know How to Win :(","time_posted":"10 hours ago"},{"heading":"How to keep up damage as jhin?","time_posted":"1 day ago"},{"heading":"Top lane wave states as a weak duellist / early game please help","time_posted":"1 day ago"}],"rules":["Golden Rule","Promote Critical Thinking","No Rant/Rage Posts","Use the Megathreads","Avoid Frequently Covered Topics","Serious Replies Only","Relevancy Rule","No Paid Services","External Content Restrictions","AMAs Must Be Preapproved"],"subreddits":{"Related Communities":{"r/wildrift":"157,715 members","r/MordekaiserMains":"39,829 members","r/fizzmains":"16,275 members","r/KledMains":"19,175 members","r/ARAM":"23,851 members","r/GarenMains":"26,417 members","r/nasusmains":"19,558 members","r/ekkomains":"34,644 members","r/ADCMains":"27,257 members","r/RakanMains":"20,397 members"}},"about":{"header":"About Community","description":"SummonerSchool is a subreddit dedicated to providing free help and resources for League of Legends players, new and veterans, to learn and improve. Ask questions, find answers, and spark discussions! We also offer a variety of resources and events to help enhance your experience. Please read the rules before posting!","created":"Created Dec 28, 2011","stats":["615k Learning","761 Teaching"]},"other_information":[{"header":"Rank Flair","description":"Flairs are back!\nClick here and follow the instructions to register for your self-updating rank flair.\nPlease note, the new flair system is currently in the testing phase so some hiccups and downtime are to be expected."}]}