{"time_collected":"2023-03-08 11:11:31.529008-05:00","top_headers":[{"heading":"Syftet med r/SwedishProblems","time_posted":"1 month ago"},{"heading":"Hur fan använder man en stekhäll","time_posted":"3 hours ago"},{"heading":"Hur svårt ska det vara att vrida på en spak?","time_posted":"9 hours ago"},{"heading":"Varför är alla färskvaror så dålig kvalite?","time_posted":"6 hours ago"},{"heading":"Till alla er som parkerar utanför ens fönster bara för att spela musik med dånande bas mitt i natten...","time_posted":"16 hours ago"},{"heading":"Folk på blocket...","time_posted":"1 day ago"},{"heading":"Hej-ing","time_posted":"21 hours ago"},{"heading":"112 Aina säsong 3","time_posted":"2 days ago"}],"rules":["Only posts in English or Swedish are allowed","No meta-reddit (posts about reddit, or facebook etc). Posts should apply to the outside world.","Problems must apply to Swedes, complaints about Denmark and other nations don't count.","Submission titles must be sufficiently descriptive of a problem where possible.","This is not r/socialthandikappad or r/pinsamt"],"subreddits":{"Bra svenska subreddits":{"r/sweden":"508,923 members","r/Asksweddit":"25,225 members","r/frittsnack":"1,597 members"}},"about":{"header":"About Community","description":"Swedish spin off on r/britishproblems. Please make sure your post is relevant to Sweden!","created":"Created Jan 4, 2013","stats":["217k Members","730 Online"]},"other_information":[]}