{"time_collected":"2023-03-08 22:21:33.629289-05:00","top_headers":[{"heading":"hear me out guys","time_posted":"2 days ago"},{"heading":"Caption This?","time_posted":"2 days ago"},{"heading":"Every Time","time_posted":"4 days ago"},{"heading":"Recently tried out Eleven Labs, and I just had to share this lol","time_posted":"4 days ago"}],"subreddits":{},"about":{"header":"About Community","description":"Memes of the 2011 MMORPG Star Wars: The Old Republic","created":"Created Mar 16, 2019","stats":["16.3k Sith Warriors","4 Feeling Baras' anger","Top 5% Ranked by Size"]},"other_information":[]}