{"time_collected":"2023-03-06 23:24:11.158010-05:00","top_headers":[{"heading":"The Handmaid's Tale S05E10 \"Safe\" - Post Episode Discussion","time_posted":"4 months ago"},{"heading":"No more posts about June or anyone else staring, please!","time_posted":"4 months ago"},{"heading":"[Spoilers All] I composed a medley based on the show's soundtrack, with scenes! I hope you like it.","time_posted":"3 days ago"},{"heading":"commander waterford edit (no spoilers)","time_posted":"4 days ago"},{"heading":"For the Sam Jaeger fans - a good podcast interview","time_posted":"4 days ago"}],"rules":["Spoiler Tags [S5 Only]","Don't be a jerk","Specific Rules (Removal & Ban)","No advertising, private subreddits, self-promotion"],"subreddits":{"Related Communities":{"r/htgawm":"54,134 members","r/Outlander":"70,142 members","r/asoiaf":"866,941 members","r/theumbrellaacademy":"60,010 members","r/GoodGirls":"20,536 members","r/thewalkingdead":"1,580,588 members","r/greysanatomy":"186,086 members","r/Bones":"20,283 members","r/gameofthrones":"3,207,227 members","r/ManifestNBC":"39,339 members"}},"about":{"header":"About Community","description":"This subreddit is a place to discuss The Handmaid's Tale TV series, based on Margaret Atwood's novel of the same name. Blessed be the fruit.","created":"Created Jul 16, 2016","stats":["156k Members","64 Online","Top 1% Ranked by Size"]},"other_information":[{"header":"Welcome To The Handmaid's Tale","description":"The Handmaid's Tale is a Hulu Original Series based off Margaret Atwood's 1985 novel The Handmaid's Tale.\nHelp the moderators by reporting any threads and comments that break the community rules. Thank you!"}]}