{"time_collected":"2023-03-06 23:16:01.441927-05:00","top_headers":[{"heading":"Tinder & vriendschapsdraadje - Valentijns editie 2023","time_posted":"21 days ago"},{"heading":"Maandagse Optimisme draad","time_posted":"23 hours ago"},{"heading":"The end is near...","time_posted":"11 hours ago"},{"heading":"Eerste InterCity Nieuwe Genertatie (ICNG) die klaar is voor de reizigers als deze in dienst komt. (Eerdere modellen moeten nog afgebouwd worden in de Poolse fabriek)","time_posted":"14 hours ago"},{"heading":"De mooiste gemeentevlaggen van Nederland","time_posted":"20 hours ago"}],"rules":["Adhere to Reddit content policy and reddiquette","No surveys, petitions or spam","No low-effort posts or low-effort questions","Posts must be related to the Netherlands","Titles and posts must be descriptive and objective","Do not post duplicates of previous posts","Assign your post the proper link flair; no [tags]","Adhere to the language guidelines"],"subreddits":{"Related Communities":{"r/Amsterdam":"203,418 members","r/Rotterdam":"83,849 members","r/TheHague":"25,066 members","r/ik_ihe":"197,107 members","r/cirkeltrek":"123,723 members","r/learndutch":"38,688 members"}},"about":{"header":"About Community","description":"Welcome to the largest bilingual Reddit community for sharing anything related to the Netherlands: news, sports, humor, culture and questions. Please browse our FAQ before posting!","created":"Created Feb 20, 2014","stats":["748k Subscribers","348 Online currently","Top 1% Ranked by Size"]},"other_information":[]}