{"time_collected":"2023-03-19 20:16:42.005757-04:00","top_headers":[{"heading":"Join the Official UNCLE ROGER DISCORD!","time_posted":"1 year ago"},{"heading":"Found Uncle Roger's car","time_posted":"5 hours ago"},{"heading":"WHERE YOUR WOK","time_posted":"11 hours ago"},{"heading":"HAIYAAAAA , just found this video from facebook page","time_posted":"9 hours ago"},{"heading":"FAILURE","time_posted":"2 days ago"},{"heading":"Salad steak jamie oliver","time_posted":"1 day ago"},{"heading":"I turn Uncle Roger into hot auntie FUIYOH!","time_posted":"2 days ago"}],"rules":["No hate!","Avoid sensitive topics","No NSFW content"],"subreddits":{"Related Communities":{"r/food":"23,259,570 members","r/hellofresh":"36,114 members","r/delhi":"399,624 members","r/tonightsdinner":"301,721 members","r/sushi":"414,133 members","r/Komi_san":"197,309 members"}},"about":{"header":"About Community","description":"Catching up with our favourite uncle. Post weejios, memes, fan art for Uncle Roger to react to. This is the official subreddit.","created":"Created Jul 28, 2020","stats":["62.0k nieces and nephews","11 Online","Top 5% Ranked by Size"]},"other_information":[]}