{"time_collected":"2023-03-19 21:15:05.712479-04:00","top_headers":[{"heading":"Special VPN deals","time_posted":"2 years ago"},{"heading":"VPN Comparison Table","time_posted":"2 years ago"},{"heading":"How come VPN service providers not get in trouble with illegal traffic?","time_posted":"6 hours ago"},{"heading":"Undetectable VPS providers for VPN hosting?","time_posted":"3 hours ago"},{"heading":"self hosted questions","time_posted":"24 minutes ago"},{"heading":"Affordable VPN capable router for streaming box?","time_posted":"4 hours ago"},{"heading":"Concerns about VPN rankings","time_posted":"4 hours ago"},{"heading":"Make a Notebook export vpn wifi?","time_posted":"4 hours ago"},{"heading":"Streaming services that require a local mobile number","time_posted":"3 days ago"},{"heading":"University VPN","time_posted":"3 days ago"},{"heading":"Is it ok to use ISP provided router with VPN?","time_posted":"3 days ago"}],"rules":["Remember the human","Read through the sub and FAQs","Don't name specific VPN providers","Don't ask for or give provider recommendations","Make use of official support channels","No advertising or self-promotion","No commercial or affiliate links","Back up your claims with proof","Share only trustworthy news from trustworthy sources"],"subreddits":{"Related communities":{"r/Express_VPN":"7,863 members","r/mullvadvpn":"12,184 members","r/nordvpn":"47,458 members","r/PrivateInternetAccess":"20,058 members","r/ProtonVPN":"44,444 members","r/raspberry_pi":"3,139,858 members","r/surfshark":"7,043 members","r/Windscribe":"29,719 members","r/vpnreviews":"22,940 members","r/vpncoupons":"8,523 members"}},"about":{"header":"About Community","description":"A community for VPN users and those who want to know more about them.","created":"Created Apr 28, 2009","stats":["129k Members","117 Online","Top 1% Ranked by Size"]},"other_information":[]}