{"time_collected":"2023-03-20 14:43:15.571552-04:00","top_headers":[{"heading":"The issue with posting.","time_posted":"3 years ago"},{"heading":"Converting Weber Side Burner to Infrared","time_posted":"5 hours ago"},{"heading":"SnS XL","time_posted":"1 hour ago"},{"heading":"End result","time_posted":"21 hours ago"},{"heading":"Fatty","time_posted":"22 hours ago"}],"rules":["No Spam.","No politically based comments."],"subreddits":{"Related Communities":{"r/pelletgrills":"227,569 members","r/grilling":"795,471 members","r/Traeger":"133,516 members","r/smoking":"573,639 members","r/hellofresh":"36,130 members","r/steak":"473,744 members","r/sousvide":"312,516 members","r/tonightsdinner":"301,872 members","r/KamadoJoe":"21,262 members","r/food":"23,260,054 members"}},"about":{"header":"About Community","description":"A place to discuss grills and smokers made by Weber-Stephen Products LLC. Topics may include news, history, discussion, pictures, memes, etc. about grills, smokers, accessories, recipes, techniques, restoration, and/or anything else Weber related.","created":"Created Oct 15, 2014","stats":["21.6k Members","41 Online"]},"other_information":[{"header":"Links & Resources","description":"Slow N Sear Buyers Guide\nWeber Kettle Club\nWeber Recipes"}]}